<?xml version="1.0" encoding="UTF-8"?><env:Envelope xmlns:env="http://schemas.xmlsoap.org/soap/envelope/"><env:Header></env:Header><env:Body Id="Body"><tikR:RespuestaRegFactuSistemaFacturacion xmlns:tikR="https://www2.agenciatributaria.gob.es/static_files/common/internet/dep/aplicaciones/es/aeat/tike/cont/ws/RespuestaSuministro.xsd" xmlns:tik="https://www2.agenciatributaria.gob.es/static_files/common/internet/dep/aplicaciones/es/aeat/tike/cont/ws/SuministroInformacion.xsd"><tikR:CSV>A-79UDK2PG294XMZ</tikR:CSV><tikR:DatosPresentacion><tik:NIFPresentador>B56803240</tik:NIFPresentador><tik:TimestampPresentacion>2025-06-26T15:06:36+02:00</tik:TimestampPresentacion></tikR:DatosPresentacion><tikR:Cabecera><tik:ObligadoEmision><tik:NombreRazon>SOFTCRAFTER S.L.</tik:NombreRazon><tik:NIF>B56803240</tik:NIF></tik:ObligadoEmision></tikR:Cabecera><tikR:TiempoEsperaEnvio>60</tikR:TiempoEsperaEnvio><tikR:EstadoEnvio>Correcto</tikR:EstadoEnvio><tikR:RespuestaLinea><tikR:IDFactura><tik:IDEmisorFactura>B56803240</tik:IDEmisorFactura><tik:NumSerieFactura>FACT2024-010</tik:NumSerieFactura><tik:FechaExpedicionFactura>25-06-2025</tik:FechaExpedicionFactura></tikR:IDFactura><tikR:Operacion><tik:TipoOperacion>Anulacion</tik:TipoOperacion></tikR:Operacion><tikR:EstadoRegistro>Correcto</tikR:EstadoRegistro></tikR:RespuestaLinea></tikR:RespuestaRegFactuSistemaFacturacion></env:Body></env:Envelope>